[
  {
    "id": "plan-20260603011733-01",
    "title": "崩落域の記憶断片追加",
    "summary": "/nullに断片化したテキストを追加し、「なにかがあった」という印象を与える。",
    "reason": "崩落域への反応が確認されており、さらなる深みで滞在時間が伸びる可能性がある。",
    "targets": [
      "/null"
    ],
    "implementationSize": "small",
    "status": "approved",
    "createdAt": "2026-06-03T01:17:33.427080+00:00",
    "source": "fallback"
  },
  {
    "id": "plan-20260603011733-02",
    "title": "観測域と信号域の隠れた導線",
    "summary": "/observationから/signalへの意図的に薄い接続リンクを追加する。",
    "reason": "両ページとも反応があり、接続することで回遊率が向上する可能性がある。",
    "targets": [
      "/observation",
      "/signal"
    ],
    "implementationSize": "small",
    "status": "pending",
    "createdAt": "2026-06-03T01:17:33.427080+00:00",
    "source": "fallback"
  },
  {
    "id": "plan-20260603011733-03",
    "title": "外部境界テキストの変質",
    "summary": "/outsideの接続テキストを壊れた形式に変更し、境界の異常感を演出する。",
    "reason": "KYOUKAIの世界観強化のため、外部接続を「狂った境界」として演出する。",
    "targets": [
      "/outside"
    ],
    "implementationSize": "small",
    "status": "pending",
    "createdAt": "2026-06-03T01:17:33.427080+00:00",
    "source": "fallback"
  }
]